concopilot/__init__.py
concopilot/basic/__init__.py
concopilot/basic/copilot/__init__.py
concopilot/basic/interface/__init__.py
concopilot/basic/interface/cmd/__init__.py
concopilot/basic/interface/cmd/interface.py
concopilot/basic/interface/duplex/__init__.py
concopilot/basic/message/__init__.py
concopilot/basic/message/manager/__init__.py
concopilot/basic/message/manager/jsonmanager/__init__.py
concopilot/basic/message/manager/jsonmanager/manager.py
concopilot/basic/message/manager/strmanager/__init__.py
concopilot/basic/message/manager/strmanager/manager.py
concopilot/basic/plugin/__init__.py
concopilot/basic/plugin/manager/__init__.py
concopilot/basic/resource/__init__.py
concopilot/basic/resource/category/__init__.py
concopilot/basic/resource/category/disk/__init__.py
concopilot/basic/resource/manager/__init__.py
concopilot/basic/storage/__init__.py
concopilot/basic/storage/disk/__init__.py
concopilot/basic/storage/disk/storage.py
concopilot/framework/__init__.py
concopilot/framework/copilot.py
concopilot/framework/run.py
concopilot/framework/asset/__init__.py
concopilot/framework/asset/asset.py
concopilot/framework/asset/asset_regex.py
concopilot/framework/cerebrum/__init__.py
concopilot/framework/cerebrum/cerebrum.py
concopilot/framework/context/__init__.py
concopilot/framework/context/context.py
concopilot/framework/identity/__init__.py
concopilot/framework/identity/identity.py
concopilot/framework/interactor/__init__.py
concopilot/framework/interactor/interactor.py
concopilot/framework/interface/__init__.py
concopilot/framework/interface/duplex.py
concopilot/framework/interface/interface.py
concopilot/framework/interface/simplex.py
concopilot/framework/message/__init__.py
concopilot/framework/message/manager.py
concopilot/framework/message/message.py
concopilot/framework/plugin/__init__.py
concopilot/framework/plugin/manager.py
concopilot/framework/plugin/plugin.py
concopilot/framework/plugin/promptgenerator.py
concopilot/framework/resource/__init__.py
concopilot-0.0.5.dist-info/LICENSE
concopilot-0.0.5.dist-info/METADATA
concopilot-0.0.5.dist-info/WHEEL
concopilot-0.0.5.dist-info/entry_points.txt
concopilot-0.0.5.dist-info/top_level.txt
concopilot-0.0.5.dist-info/RECORD
