Metadata-Version: 2.1
Name: concopilot
Version: 0.0.5
Summary: ConCopilot defines standards and common interfaces that would be helpful to make each part of a copilot reusable, replaceable, portable, and flexible.
Author-email: ZHONG Weikun <zhong.weikun@live.com>
Project-URL: Homepage, https://github.com/ConCopilot/concopilot
Project-URL: Bug Tracker, https://github.com/ConCopilot/concopilot/issues
Classifier: Programming Language :: Python :: 3
Classifier: Operating System :: OS Independent
Requires-Python: >=3.8
License-File: LICENSE
Requires-Dist: PyYAML
Requires-Dist: numpy
Requires-Dist: validators >=0.20.7
Requires-Dist: python-gnupg
Requires-Dist: requests
Requires-Dist: pycryptodome
Requires-Dist: tqdm
